[
    {
        "往生者姓名": "徐國卿",
        "使用設備項目": "景行無煙豎靈-008",
        "開始時間": "114\/08\/19",
        "結束時間": "114\/08\/2210:00",
        "代辦業者": "江山殯葬禮儀社",
        "公祭時間": ""
    },
    {
        "往生者姓名": "徐國卿",
        "使用設備項目": "冷凍室-143",
        "開始時間": "114\/08\/1900:55",
        "結束時間": "114\/08\/2108:00",
        "代辦業者": "江山殯葬禮儀社",
        "公祭時間": ""
    },
    {
        "往生者姓名": "徐國卿",
        "使用設備項目": "洗化室03",
        "開始時間": "114\/08\/21",
        "結束時間": "114\/08\/21",
        "代辦業者": "江山殯葬禮儀社",
        "公祭時間": ""
    },
    {
        "往生者姓名": "徐國卿",
        "使用設備項目": "遺體火化",
        "開始時間": "114\/08\/22",
        "結束時間": "114\/08\/22",
        "代辦業者": "江山殯葬禮儀社",
        "公祭時間": ""
    },
    {
        "往生者姓名": "徐國卿",
        "使用設備項目": "停屍間",
        "開始時間": "114\/08\/22",
        "結束時間": "114\/08\/2208:00",
        "代辦業者": "江山殯葬禮儀社",
        "公祭時間": ""
    },
    {
        "往生者姓名": "徐國卿",
        "使用設備項目": "入殮(助念)室05",
        "開始時間": "114\/08\/2208:00",
        "結束時間": "114\/08\/2210:00",
        "代辦業者": "江山殯葬禮儀社",
        "公祭時間": "08:30"
    }
]