[
    {
        "往生者姓名": "吳國精",
        "使用設備項目": "入殮(助念)室05",
        "開始時間": "114\/08\/2322:00",
        "結束時間": "114\/08\/2324:00",
        "代辦業者": "圓生生命禮儀社",
        "公祭時間": ""
    },
    {
        "往生者姓名": "吳國精",
        "使用設備項目": "洗化室01",
        "開始時間": "114\/08\/24",
        "結束時間": "114\/08\/24",
        "代辦業者": "圓生生命禮儀社",
        "公祭時間": ""
    },
    {
        "往生者姓名": "吳國精",
        "使用設備項目": "停屍間",
        "開始時間": "114\/08\/2400:30",
        "結束時間": "114\/08\/2416:00",
        "代辦業者": "圓生生命禮儀社",
        "公祭時間": ""
    },
    {
        "往生者姓名": "吳國精",
        "使用設備項目": "和平堂-58",
        "開始時間": "114\/08\/2414:10",
        "結束時間": "114\/09\/0113:50",
        "代辦業者": "圓生生命禮儀社",
        "公祭時間": "10:00"
    },
    {
        "往生者姓名": "吳國精",
        "使用設備項目": "入殮室01",
        "開始時間": "114\/08\/2416:00",
        "結束時間": "114\/08\/2418:00",
        "代辦業者": "圓生生命禮儀社",
        "公祭時間": ""
    },
    {
        "往生者姓名": "吳國精",
        "使用設備項目": "遺體火化",
        "開始時間": "114\/09\/01",
        "結束時間": "114\/09\/01",
        "代辦業者": "圓生生命禮儀社",
        "公祭時間": ""
    }
]