[
    {
        "往生者姓名": "馮佳琪",
        "使用設備項目": "冷凍室-058",
        "開始時間": "114\/08\/2123:13",
        "結束時間": "114\/08\/2408:00",
        "代辦業者": "萬安生命科技股份有限公司",
        "公祭時間": ""
    },
    {
        "往生者姓名": "馮佳琪",
        "使用設備項目": "洗化室07",
        "開始時間": "114\/08\/2412:00",
        "結束時間": "114\/08\/2415:00",
        "代辦業者": "萬安生命科技股份有限公司",
        "公祭時間": ""
    },
    {
        "往生者姓名": "馮佳琪",
        "使用設備項目": "遺體火化",
        "開始時間": "114\/08\/25",
        "結束時間": "114\/08\/25",
        "代辦業者": "萬安生命科技股份有限公司",
        "公祭時間": ""
    },
    {
        "往生者姓名": "馮佳琪",
        "使用設備項目": "停屍間",
        "開始時間": "114\/08\/25",
        "結束時間": "114\/08\/2508:00",
        "代辦業者": "萬安生命科技股份有限公司",
        "公祭時間": ""
    },
    {
        "往生者姓名": "馮佳琪",
        "使用設備項目": "入殮室09",
        "開始時間": "114\/08\/2508:00",
        "結束時間": "114\/08\/2510:00",
        "代辦業者": "萬安生命科技股份有限公司",
        "公祭時間": "無公祭"
    }
]