[
    {
        "往生者姓名": "黃指揮",
        "使用設備項目": "冷凍室-133",
        "開始時間": "114\/08\/3123:20",
        "結束時間": "114\/09\/0909:00",
        "代辦業者": "台灣仁本生命科技股份有限公司",
        "公祭時間": ""
    },
    {
        "往生者姓名": "黃指揮",
        "使用設備項目": "洗化室01",
        "開始時間": "114\/09\/09",
        "結束時間": "114\/09\/09",
        "代辦業者": "台灣仁本生命科技股份有限公司",
        "公祭時間": ""
    },
    {
        "往生者姓名": "黃指揮",
        "使用設備項目": "停屍間",
        "開始時間": "114\/09\/10",
        "結束時間": "114\/09\/1009:00",
        "代辦業者": "台灣仁本生命科技股份有限公司",
        "公祭時間": ""
    },
    {
        "往生者姓名": "黃指揮",
        "使用設備項目": "入殮室02",
        "開始時間": "114\/09\/1009:00",
        "結束時間": "114\/09\/1011:00",
        "代辦業者": "台灣仁本生命科技股份有限公司",
        "公祭時間": "無公祭"
    },
    {
        "往生者姓名": "黃指揮",
        "使用設備項目": "遺體火化",
        "開始時間": "114\/09\/10",
        "結束時間": "114\/09\/10",
        "代辦業者": "台灣仁本生命科技股份有限公司",
        "公祭時間": ""
    }
]