[
    {
        "往生者姓名": "魏聯明",
        "使用設備項目": "冷凍室-164",
        "開始時間": "114\/09\/0715:30",
        "結束時間": "114\/09\/0912:00",
        "代辦業者": "昆霖禮儀社",
        "公祭時間": ""
    },
    {
        "往生者姓名": "魏聯明",
        "使用設備項目": "豎靈區-050",
        "開始時間": "114\/09\/08",
        "結束時間": "114\/09\/1014:00",
        "代辦業者": "昆霖禮儀社",
        "公祭時間": ""
    },
    {
        "往生者姓名": "魏聯明",
        "使用設備項目": "洗化室03",
        "開始時間": "114\/09\/09",
        "結束時間": "114\/09\/09",
        "代辦業者": "昆霖禮儀社",
        "公祭時間": ""
    },
    {
        "往生者姓名": "魏聯明",
        "使用設備項目": "停屍間",
        "開始時間": "114\/09\/10",
        "結束時間": "114\/09\/1012:00",
        "代辦業者": "昆霖禮儀社",
        "公祭時間": ""
    },
    {
        "往生者姓名": "魏聯明",
        "使用設備項目": "入殮室03",
        "開始時間": "114\/09\/1012:00",
        "結束時間": "114\/09\/1014:00",
        "代辦業者": "昆霖禮儀社",
        "公祭時間": ""
    },
    {
        "往生者姓名": "魏聯明",
        "使用設備項目": "永安堂-23",
        "開始時間": "114\/09\/1014:10",
        "結束時間": "114\/09\/1313:50",
        "代辦業者": "昆霖禮儀社",
        "公祭時間": ""
    },
    {
        "往生者姓名": "魏聯明",
        "使用設備項目": "和平堂-50",
        "開始時間": "114\/09\/1314:10",
        "結束時間": "114\/09\/1713:50",
        "代辦業者": "昆霖禮儀社",
        "公祭時間": "無公祭"
    },
    {
        "往生者姓名": "魏聯明",
        "使用設備項目": "遺體火化",
        "開始時間": "114\/09\/17",
        "結束時間": "114\/09\/17",
        "代辦業者": "昆霖禮儀社",
        "公祭時間": ""
    }
]