[
    {
        "往生者姓名": "陳黃惠雀",
        "使用設備項目": "無煙豎靈區-012",
        "開始時間": "114\/09\/04",
        "結束時間": "114\/09\/0416:00",
        "代辦業者": "蓮心葬儀社",
        "公祭時間": ""
    },
    {
        "往生者姓名": "陳黃惠雀",
        "使用設備項目": "冷凍室-148",
        "開始時間": "114\/09\/0400:53",
        "結束時間": "114\/09\/1006:00",
        "代辦業者": "蓮心葬儀社",
        "公祭時間": ""
    },
    {
        "往生者姓名": "陳黃惠雀",
        "使用設備項目": "洗化室02",
        "開始時間": "114\/09\/10",
        "結束時間": "114\/09\/10",
        "代辦業者": "蓮心葬儀社",
        "公祭時間": ""
    },
    {
        "往生者姓名": "陳黃惠雀",
        "使用設備項目": "停屍間",
        "開始時間": "114\/09\/11",
        "結束時間": "114\/09\/1106:00",
        "代辦業者": "蓮心葬儀社",
        "公祭時間": ""
    },
    {
        "往生者姓名": "陳黃惠雀",
        "使用設備項目": "入殮室03",
        "開始時間": "114\/09\/1106:00",
        "結束時間": "114\/09\/1108:00",
        "代辦業者": "蓮心葬儀社",
        "公祭時間": "無公祭"
    },
    {
        "往生者姓名": "陳黃惠雀",
        "使用設備項目": "遺體火化",
        "開始時間": "114\/09\/11",
        "結束時間": "114\/09\/11",
        "代辦業者": "蓮心葬儀社",
        "公祭時間": ""
    }
]