[
    {
        "往生者姓名": "李育田",
        "使用設備項目": "冷凍室-172",
        "開始時間": "114\/09\/2414:28",
        "結束時間": "114\/09\/2714:00",
        "代辦業者": "自成宇宙生命禮儀社",
        "公祭時間": ""
    },
    {
        "往生者姓名": "李育田",
        "使用設備項目": "豎靈區-003",
        "開始時間": "114\/09\/25",
        "結束時間": "114\/09\/28",
        "代辦業者": "自成宇宙生命禮儀社",
        "公祭時間": ""
    },
    {
        "往生者姓名": "李育田",
        "使用設備項目": "洗化室01",
        "開始時間": "114\/09\/27",
        "結束時間": "114\/09\/27",
        "代辦業者": "自成宇宙生命禮儀社",
        "公祭時間": ""
    },
    {
        "往生者姓名": "李育田",
        "使用設備項目": "停屍間",
        "開始時間": "114\/09\/28",
        "結束時間": "114\/09\/2814:00",
        "代辦業者": "自成宇宙生命禮儀社",
        "公祭時間": ""
    },
    {
        "往生者姓名": "李育田",
        "使用設備項目": "入殮室09",
        "開始時間": "114\/09\/2814:00",
        "結束時間": "114\/09\/2816:00",
        "代辦業者": "自成宇宙生命禮儀社",
        "公祭時間": ""
    },
    {
        "往生者姓名": "李育田",
        "使用設備項目": "和平堂-03-1",
        "開始時間": "114\/09\/2814:10",
        "結束時間": "114\/10\/0413:50",
        "代辦業者": "自成宇宙生命禮儀社",
        "公祭時間": "07:50"
    },
    {
        "往生者姓名": "李育田",
        "使用設備項目": "遺體火化",
        "開始時間": "114\/10\/04",
        "結束時間": "114\/10\/04",
        "代辦業者": "自成宇宙生命禮儀社",
        "公祭時間": ""
    }
]