[
    {
        "往生者姓名": "凃錦山",
        "使用設備項目": "冷凍室-207",
        "開始時間": "115\/02\/1518:34",
        "結束時間": "115\/02\/2013:00",
        "代辦業者": "修寧禮儀社",
        "公祭時間": ""
    },
    {
        "往生者姓名": "凃錦山",
        "使用設備項目": "無煙豎靈區-009",
        "開始時間": "115\/02\/16",
        "結束時間": "115\/02\/2115:00",
        "代辦業者": "修寧禮儀社",
        "公祭時間": ""
    },
    {
        "往生者姓名": "凃錦山",
        "使用設備項目": "入殮室01",
        "開始時間": "115\/02\/1710:00",
        "結束時間": "115\/02\/1712:00",
        "代辦業者": "修寧禮儀社",
        "公祭時間": ""
    },
    {
        "往生者姓名": "凃錦山",
        "使用設備項目": "洗化室04",
        "開始時間": "115\/02\/20",
        "結束時間": "115\/02\/20",
        "代辦業者": "修寧禮儀社",
        "公祭時間": ""
    },
    {
        "往生者姓名": "凃錦山",
        "使用設備項目": "停屍間",
        "開始時間": "115\/02\/21",
        "結束時間": "115\/02\/2113:00",
        "代辦業者": "修寧禮儀社",
        "公祭時間": ""
    },
    {
        "往生者姓名": "凃錦山",
        "使用設備項目": "入殮室02",
        "開始時間": "115\/02\/2113:00",
        "結束時間": "115\/02\/2115:00",
        "代辦業者": "修寧禮儀社",
        "公祭時間": ""
    },
    {
        "往生者姓名": "凃錦山",
        "使用設備項目": "和平堂-35",
        "開始時間": "115\/02\/2114:10",
        "結束時間": "115\/02\/2513:50",
        "代辦業者": "修寧禮儀社",
        "公祭時間": ""
    },
    {
        "往生者姓名": "凃錦山",
        "使用設備項目": "遺體火化",
        "開始時間": "115\/02\/25",
        "結束時間": "115\/02\/25",
        "代辦業者": "修寧禮儀社",
        "公祭時間": ""
    },
    {
        "往生者姓名": "凃錦山",
        "使用設備項目": "景福廳",
        "開始時間": "115\/02\/2508:30",
        "結束時間": "115\/02\/2511:00",
        "代辦業者": "修寧禮儀社",
        "公祭時間": "09:30"
    }
]