[
    {
        "往生者姓名": "王博文",
        "使用設備項目": "冷凍室-021",
        "開始時間": "114\/12\/2104:00",
        "結束時間": "",
        "代辦業者": "真仙樂禮儀社",
        "公祭時間": ""
    },
    {
        "往生者姓名": "王博文",
        "使用設備項目": "洗化室03",
        "開始時間": "114\/12\/23",
        "結束時間": "114\/12\/23",
        "代辦業者": "真仙樂禮儀社",
        "公祭時間": ""
    },
    {
        "往生者姓名": "王博文",
        "使用設備項目": "遺體火化",
        "開始時間": "114\/12\/29",
        "結束時間": "114\/12\/29",
        "代辦業者": "真仙樂禮儀社",
        "公祭時間": "09:30（館外）"
    }
]