[
    {
        "往生者姓名": "蘇榮章",
        "使用設備項目": "景行無煙豎靈-021",
        "開始時間": "114\/12\/04",
        "結束時間": "114\/12\/1609:00",
        "代辦業者": "星宇禮儀有限公司",
        "公祭時間": ""
    },
    {
        "往生者姓名": "蘇榮章",
        "使用設備項目": "冷凍室-216",
        "開始時間": "114\/12\/0411:29",
        "結束時間": "114\/12\/1508:00",
        "代辦業者": "星宇禮儀有限公司",
        "公祭時間": ""
    },
    {
        "往生者姓名": "蘇榮章",
        "使用設備項目": "入殮室04",
        "開始時間": "114\/12\/0510:00",
        "結束時間": "114\/12\/0512:00",
        "代辦業者": "星宇禮儀有限公司",
        "公祭時間": ""
    },
    {
        "往生者姓名": "蘇榮章",
        "使用設備項目": "入殮室02",
        "開始時間": "114\/12\/1012:00",
        "結束時間": "114\/12\/1016:00",
        "代辦業者": "星宇禮儀有限公司",
        "公祭時間": ""
    },
    {
        "往生者姓名": "蘇榮章",
        "使用設備項目": "洗化室06",
        "開始時間": "114\/12\/15",
        "結束時間": "114\/12\/15",
        "代辦業者": "星宇禮儀有限公司",
        "公祭時間": ""
    },
    {
        "往生者姓名": "蘇榮章",
        "使用設備項目": "入殮室02",
        "開始時間": "114\/12\/1508:00",
        "結束時間": "114\/12\/1516:00",
        "代辦業者": "星宇禮儀有限公司",
        "公祭時間": ""
    },
    {
        "往生者姓名": "蘇榮章",
        "使用設備項目": "懷澤廳",
        "開始時間": "114\/12\/1512:30",
        "結束時間": "114\/12\/1515:00",
        "代辦業者": "星宇禮儀有限公司",
        "公祭時間": "10:00"
    },
    {
        "往生者姓名": "蘇榮章",
        "使用設備項目": "停屍間",
        "開始時間": "114\/12\/16",
        "結束時間": "114\/12\/1608:00",
        "代辦業者": "星宇禮儀有限公司",
        "公祭時間": ""
    },
    {
        "往生者姓名": "蘇榮章",
        "使用設備項目": "入殮室02",
        "開始時間": "114\/12\/1608:00",
        "結束時間": "114\/12\/1610:00",
        "代辦業者": "星宇禮儀有限公司",
        "公祭時間": ""
    },
    {
        "往生者姓名": "蘇榮章",
        "使用設備項目": "遺體火化",
        "開始時間": "114\/12\/16",
        "結束時間": "114\/12\/16",
        "代辦業者": "星宇禮儀有限公司",
        "公祭時間": ""
    },
    {
        "往生者姓名": "蘇榮章",
        "使用設備項目": "懷澤廳",
        "開始時間": "114\/12\/1608:30",
        "結束時間": "114\/12\/1611:00",
        "代辦業者": "星宇禮儀有限公司",
        "公祭時間": ""
    }
]