{
    "date": "114-11-22",
    "count": 2,
    "records": [
        {
            "code": "S02",
            "公祭時間": "10:00",
            "公祭地點": "明德廳",
            "輓額": "✓(有)",
            "往生者": "李孟峰",
            "性別": "男",
            "年次": "055",
            "戶籍地": "臺南市中西區",
            "SID": "A1141104031"
        },
        {
            "code": "S05",
            "公祭時間": "12:10",
            "公祭地點": "懷悌廳",
            "輓額": "✓(有)",
            "往生者": "薛發",
            "性別": "男",
            "年次": "007",
            "戶籍地": "臺南市南區",
            "SID": "A1141030025"
        }
    ]
}