{
    "date": "114-10-12",
    "count": 27,
    "records": [
        {
            "code": "S17",
            "公祭時間": "07:20",
            "公祭地點": "和平堂-42",
            "輓額": "✓(有)",
            "往生者": "高德助",
            "性別": "男",
            "年次": "059",
            "戶籍地": "臺南市新市區",
            "SID": "A1141001024"
        },
        {
            "code": "S15",
            "公祭時間": "07:30",
            "公祭地點": "和平堂-07",
            "輓額": "✓",
            "往生者": "林沈淑君",
            "性別": "女",
            "年次": "032",
            "戶籍地": "臺南市南區",
            "SID": "A1141004014"
        },
        {
            "code": "S15",
            "公祭時間": "07:40",
            "公祭地點": "和平堂-03",
            "輓額": "✓",
            "往生者": "楊翊楷",
            "性別": "男",
            "年次": "097",
            "戶籍地": "臺南市歸仁區",
            "SID": "A1141004025"
        },
        {
            "code": "S15",
            "公祭時間": "07:40",
            "公祭地點": "和平堂-02",
            "輓額": "✓(有)",
            "往生者": "林振華",
            "性別": "男",
            "年次": "043",
            "戶籍地": "臺南市安南區",
            "SID": "A1141002005"
        },
        {
            "code": "S23",
            "公祭時間": "07:50",
            "公祭地點": "和平堂-59",
            "輓額": "✓",
            "往生者": "許施玉秋",
            "性別": "女",
            "年次": "026",
            "戶籍地": "臺南市東區",
            "SID": "A1141004009"
        },
        {
            "code": "S16",
            "公祭時間": "08:00",
            "公祭地點": "和平堂-33-1",
            "輓額": "✓",
            "往生者": "李金鞠",
            "性別": "男",
            "年次": "038",
            "戶籍地": "臺南市永康區",
            "SID": "A1141004033"
        },
        {
            "code": "S15",
            "公祭時間": "08:00",
            "公祭地點": "和平堂-09",
            "輓額": "✓(有)",
            "往生者": "王崑成",
            "性別": "男",
            "年次": "044",
            "戶籍地": "臺南市玉井區",
            "SID": "A1141003001"
        },
        {
            "code": "S20",
            "公祭時間": "08:00",
            "公祭地點": "和平堂-58",
            "輓額": "✓(有)",
            "往生者": "楊天在",
            "性別": "男",
            "年次": "055",
            "戶籍地": "臺南市南區",
            "SID": "A1141002015"
        },
        {
            "code": "S17",
            "公祭時間": "08:30",
            "公祭地點": "和平堂-38",
            "輓額": "✓(有)",
            "往生者": "溫正謙",
            "性別": "男",
            "年次": "040",
            "戶籍地": "臺南市安南區",
            "SID": "A1141001004"
        },
        {
            "code": "S09",
            "公祭時間": "08:30",
            "公祭地點": "懷恩廳（婉拒民代公祭）",
            "輓額": "✓(有)",
            "往生者": "蘇義益",
            "性別": "男",
            "年次": "042",
            "戶籍地": "臺南市中西區",
            "SID": "A1141002036"
        },
        {
            "code": "S17",
            "公祭時間": "08:45",
            "公祭地點": "和平堂-37",
            "輓額": "✓(有)",
            "往生者": "吳辜微",
            "性別": "女",
            "年次": "018",
            "戶籍地": "臺南市安南區",
            "SID": "A1141001014"
        },
        {
            "code": "S06",
            "公祭時間": "09:40",
            "公祭地點": "懷澤廳",
            "輓額": "✓(有)",
            "往生者": "黃清川",
            "性別": "男",
            "年次": "022",
            "戶籍地": "臺南市中西區",
            "SID": "A1141003003"
        },
        {
            "code": "S10",
            "公祭時間": "09:45",
            "公祭地點": "永安堂-20",
            "輓額": "",
            "往生者": "吳洪鑾",
            "性別": "女",
            "年次": "025",
            "戶籍地": "臺南市東區",
            "SID": "A1141003019"
        },
        {
            "code": "S15",
            "公祭時間": "09:50",
            "公祭地點": "和平堂-11",
            "輓額": "✓(有)",
            "往生者": "李錦堂",
            "性別": "男",
            "年次": "043",
            "戶籍地": "臺南市安南區",
            "SID": "A1140928004"
        },
        {
            "code": "S15",
            "公祭時間": "09:50",
            "公祭地點": "和平堂-13",
            "輓額": "✓(有)",
            "往生者": "楊德福",
            "性別": "男",
            "年次": "037",
            "戶籍地": "臺南市北區",
            "SID": "A1141001013"
        },
        {
            "code": "S19",
            "公祭時間": "09:50",
            "公祭地點": "和平堂-52",
            "輓額": "✓(有)",
            "往生者": "吳楊月娥",
            "性別": "女",
            "年次": "041",
            "戶籍地": "臺南市安南區",
            "SID": "A1141002006"
        },
        {
            "code": "S20",
            "公祭時間": "09:50",
            "公祭地點": "和平堂-57",
            "輓額": "✓(有)",
            "往生者": "呂麗紅",
            "性別": "女",
            "年次": "054",
            "戶籍地": "臺南市南區",
            "SID": "A1141002033"
        },
        {
            "code": "S19",
            "公祭時間": "10:00",
            "公祭地點": "和平堂-53-1",
            "輓額": "✓(有)",
            "往生者": "劉陳茶",
            "性別": "女",
            "年次": "035",
            "戶籍地": "臺南市安南區",
            "SID": "A1141002034"
        },
        {
            "code": "S01",
            "公祭時間": "10:10",
            "公祭地點": "景福廳",
            "輓額": "✓(有)",
            "往生者": "鄭玉山",
            "性別": "男",
            "年次": "052",
            "戶籍地": "臺南市永康區",
            "SID": "A1141002001"
        },
        {
            "code": "S08",
            "公祭時間": "10:10",
            "公祭地點": "懷親廳",
            "輓額": "✓(有)",
            "往生者": "陳項",
            "性別": "女",
            "年次": "019",
            "戶籍地": "臺南市佳里區",
            "SID": "A1140930005"
        },
        {
            "code": "S17",
            "公祭時間": "10:10",
            "公祭地點": "和平堂-41",
            "輓額": "✓(有)",
            "往生者": "黃董綉英",
            "性別": "女",
            "年次": "019",
            "戶籍地": "臺南市永康區",
            "SID": "A1141003005"
        },
        {
            "code": "S19",
            "公祭時間": "10:10",
            "公祭地點": "和平堂-53",
            "輓額": "✓(有)",
            "往生者": "陳榮五",
            "性別": "男",
            "年次": "031",
            "戶籍地": "臺南市北區",
            "SID": "A1141003014"
        },
        {
            "code": "S10",
            "公祭時間": "無公祭",
            "公祭地點": "永安堂-09",
            "輓額": "",
            "往生者": "蘇義雄",
            "性別": "男",
            "年次": "027",
            "戶籍地": "臺南市東山區",
            "SID": "A1141001012"
        },
        {
            "code": "S15",
            "公祭時間": "無公祭",
            "公祭地點": "和平堂-17（婉拒公祭）",
            "輓額": "",
            "往生者": "程許粉",
            "性別": "女",
            "年次": "038",
            "戶籍地": "臺南市新化區",
            "SID": "A1141002026"
        },
        {
            "code": "S15",
            "公祭時間": "無公祭",
            "公祭地點": "和平堂-26",
            "輓額": "",
            "往生者": "嚴苑玉",
            "性別": "女",
            "年次": "032",
            "戶籍地": "臺南市北區",
            "SID": "A1141003004"
        },
        {
            "code": "S18",
            "公祭時間": "無公祭",
            "公祭地點": "和平堂-43-1",
            "輓額": "",
            "往生者": "廖吳麗傾",
            "性別": "女",
            "年次": "041",
            "戶籍地": "臺南市永康區",
            "SID": "A1141004032"
        },
        {
            "code": "S07",
            "公祭時間": "無公祭",
            "公祭地點": "懷慈廳",
            "輓額": "",
            "往生者": "侯淑玲",
            "性別": "女",
            "年次": "052",
            "戶籍地": "臺南市中西區",
            "SID": "A1141002004"
        }
    ]
}