{
    "date": "114-12-30",
    "count": 3,
    "records": [
        {
            "code": "S15",
            "公祭時間": "08:30",
            "公祭地點": "和平堂-22（婉拒民代公祭）",
            "輓額": "✓(有)",
            "往生者": "王滄海",
            "性別": "男",
            "年次": "054",
            "戶籍地": "臺南市歸仁區",
            "SID": "A1141222004"
        },
        {
            "code": "S18",
            "公祭時間": "09:50",
            "公祭地點": "和平堂-45",
            "輓額": "✓(有)",
            "往生者": "高蜜",
            "性別": "女",
            "年次": "026",
            "戶籍地": "臺南市安南區",
            "SID": "A1141217023"
        },
        {
            "code": "S08",
            "公祭時間": "10:15",
            "公祭地點": "懷親廳",
            "輓額": "✓(有)",
            "往生者": "陳貞夙",
            "性別": "女",
            "年次": "050",
            "戶籍地": "臺南市東區",
            "SID": "A1141220013"
        }
    ]
}