{
    "date": "114-10-08",
    "count": 3,
    "records": [
        {
            "code": "S07",
            "公祭時間": "08:30",
            "公祭地點": "懷慈廳",
            "輓額": "✓(有)",
            "往生者": "王杉義",
            "性別": "男",
            "年次": "041",
            "戶籍地": "臺南市東區",
            "SID": "A1140927002"
        },
        {
            "code": "S06",
            "公祭時間": "10:00",
            "公祭地點": "懷澤廳",
            "輓額": "✓",
            "往生者": "陳智鑫",
            "性別": "男",
            "年次": "044",
            "戶籍地": "臺南市永康區",
            "SID": "A1140928014"
        },
        {
            "code": "S05",
            "公祭時間": "無公祭",
            "公祭地點": "懷悌廳（婉拒民代公祭）",
            "輓額": "",
            "往生者": "陳麗美",
            "性別": "女",
            "年次": "039",
            "戶籍地": "臺南市中西區",
            "SID": "A1140930025"
        }
    ]
}