{
    "date": "115-06-25",
    "count": 17,
    "records": [
        {
            "code": "S15",
            "公祭時間": "07:30",
            "公祭地點": "和平堂-05",
            "輓額": "✓(有)",
            "往生者": "戴昆海",
            "性別": "男",
            "年次": "050",
            "戶籍地": "臺南市新市區",
            "SID": "A1150618028"
        },
        {
            "code": "S18",
            "公祭時間": "07:40",
            "公祭地點": "和平堂-46",
            "輓額": "✓(有)",
            "往生者": "陳明男",
            "性別": "男",
            "年次": "039",
            "戶籍地": "臺南市柳營區",
            "SID": "A1150618019"
        },
        {
            "code": "S07",
            "公祭時間": "08:00",
            "公祭地點": "懷慈廳",
            "輓額": "✓(有)",
            "往生者": "許宏琦",
            "性別": "男",
            "年次": "069",
            "戶籍地": "臺南市永康區",
            "SID": "A1150617014"
        },
        {
            "code": "S15",
            "公祭時間": "08:00",
            "公祭地點": "和平堂-18",
            "輓額": "✓(有)",
            "往生者": "葉郭波",
            "性別": "女",
            "年次": "027",
            "戶籍地": "臺南市關廟區",
            "SID": "A1150615002"
        },
        {
            "code": "S17",
            "公祭時間": "08:30",
            "公祭地點": "和平堂-41",
            "輓額": "✓(有)",
            "往生者": "陳明進",
            "性別": "男",
            "年次": "039",
            "戶籍地": "臺南市永康區",
            "SID": "A1150614018"
        },
        {
            "code": "S19",
            "公祭時間": "09:00",
            "公祭地點": "和平堂-52",
            "輓額": "✓(有)",
            "往生者": "于鳳儀",
            "性別": "女",
            "年次": "028",
            "戶籍地": "臺南市東區",
            "SID": "A1150617022"
        },
        {
            "code": "S15",
            "公祭時間": "09:45",
            "公祭地點": "和平堂-07",
            "輓額": "✓(有)",
            "往生者": "傅有義",
            "性別": "男",
            "年次": "046",
            "戶籍地": "臺南市南區",
            "SID": "A1150616006"
        },
        {
            "code": "S15",
            "公祭時間": "09:50",
            "公祭地點": "和平堂-19",
            "輓額": "✓(有)",
            "往生者": "鄭忠國",
            "性別": "男",
            "年次": "018",
            "戶籍地": "臺南市北區",
            "SID": "A1150615035"
        },
        {
            "code": "S15",
            "公祭時間": "09:50",
            "公祭地點": "和平堂-03",
            "輓額": "✓(有)",
            "往生者": "戴維成",
            "性別": "男",
            "年次": "070",
            "戶籍地": "臺南市南區",
            "SID": "A1150615016"
        },
        {
            "code": "S06",
            "公祭時間": "10:00",
            "公祭地點": "懷澤廳",
            "輓額": "✓(有)",
            "往生者": "莊黃阿琴",
            "性別": "女",
            "年次": "039",
            "戶籍地": "臺南市北區",
            "SID": "A1150614028"
        },
        {
            "code": "S08",
            "公祭時間": "10:00",
            "公祭地點": "懷親廳",
            "輓額": "✓(有)",
            "往生者": "張王月英",
            "性別": "女",
            "年次": "015",
            "戶籍地": "臺南市中西區",
            "SID": "A1150616012"
        },
        {
            "code": "S15",
            "公祭時間": "11:40",
            "公祭地點": "和平堂-23-1",
            "輓額": "✓(有)",
            "往生者": "張世柱",
            "性別": "男",
            "年次": "016",
            "戶籍地": "臺南市永康區",
            "SID": "A1150615001"
        },
        {
            "code": "S15",
            "公祭時間": "無公祭",
            "公祭地點": "和平堂-15",
            "輓額": "",
            "往生者": "陳志明",
            "性別": "男",
            "年次": "054",
            "戶籍地": "臺南市佳里區",
            "SID": "A1150618002"
        },
        {
            "code": "S15",
            "公祭時間": "無公祭",
            "公祭地點": "和平堂-11",
            "輓額": "",
            "往生者": "鄭顏金菊",
            "性別": "女",
            "年次": "035",
            "戶籍地": "臺南市安南區",
            "SID": "A1150616017"
        },
        {
            "code": "S20",
            "公祭時間": "無公祭",
            "公祭地點": "和平堂-58",
            "輓額": "",
            "往生者": "蔡文煌",
            "性別": "男",
            "年次": "039",
            "戶籍地": "臺南市東區",
            "SID": "A1150617024"
        },
        {
            "code": "S15",
            "公祭時間": "無公祭",
            "公祭地點": "和平堂-13-1",
            "輓額": "",
            "往生者": "吳舜彬",
            "性別": "男",
            "年次": "023",
            "戶籍地": "臺南市北區",
            "SID": "A1150618027"
        },
        {
            "code": "S05",
            "公祭時間": "無公祭",
            "公祭地點": "懷悌廳（婉拒民代公祭）",
            "輓額": "",
            "往生者": "方關海",
            "性別": "男",
            "年次": "020",
            "戶籍地": "臺南市中西區",
            "SID": "A1150614010"
        }
    ]
}