[
    {
        "往生者姓名": "蔡淑慧",
        "使用設備項目": "洗化室03",
        "開始時間": "114\/11\/25",
        "結束時間": "114\/11\/25",
        "代辦業者": "阿亮禮儀社",
        "公祭時間": ""
    },
    {
        "往生者姓名": "蔡淑慧",
        "使用設備項目": "冷凍室-164",
        "開始時間": "114\/11\/2511:30",
        "結束時間": "114\/11\/2519:00",
        "代辦業者": "阿亮禮儀社",
        "公祭時間": ""
    },
    {
        "往生者姓名": "蔡淑慧",
        "使用設備項目": "永安堂-08",
        "開始時間": "114\/11\/2514:10",
        "結束時間": "114\/12\/0113:50",
        "代辦業者": "阿亮禮儀社",
        "公祭時間": ""
    },
    {
        "往生者姓名": "蔡淑慧",
        "使用設備項目": "入殮室01",
        "開始時間": "114\/11\/2519:00",
        "結束時間": "114\/11\/2521:00",
        "代辦業者": "阿亮禮儀社",
        "公祭時間": ""
    },
    {
        "往生者姓名": "蔡淑慧",
        "使用設備項目": "和平堂-58",
        "開始時間": "114\/12\/0114:10",
        "結束時間": "114\/12\/0413:50",
        "代辦業者": "阿亮禮儀社",
        "公祭時間": ""
    },
    {
        "往生者姓名": "蔡淑慧",
        "使用設備項目": "景福廳",
        "開始時間": "114\/12\/0408:30",
        "結束時間": "114\/12\/0411:00",
        "代辦業者": "阿亮禮儀社",
        "公祭時間": "09:30"
    },
    {
        "往生者姓名": "蔡淑慧",
        "使用設備項目": "遺體火化",
        "開始時間": "114\/12\/04",
        "結束時間": "114\/12\/04",
        "代辦業者": "阿亮禮儀社",
        "公祭時間": ""
    }
]