[
    {
        "往生者姓名": "楊凱郎",
        "使用設備項目": "冷凍室-128",
        "開始時間": "115\/04\/1121:30",
        "結束時間": "115\/04\/1412:00",
        "代辦業者": "慈航禮儀社",
        "公祭時間": ""
    },
    {
        "往生者姓名": "楊凱郎",
        "使用設備項目": "洗化室04",
        "開始時間": "115\/04\/14",
        "結束時間": "115\/04\/14",
        "代辦業者": "慈航禮儀社",
        "公祭時間": ""
    },
    {
        "往生者姓名": "楊凱郎",
        "使用設備項目": "停屍間",
        "開始時間": "115\/04\/15",
        "結束時間": "115\/04\/1512:00",
        "代辦業者": "慈航禮儀社",
        "公祭時間": ""
    },
    {
        "往生者姓名": "楊凱郎",
        "使用設備項目": "入殮(助念)室05",
        "開始時間": "115\/04\/1512:00",
        "結束時間": "115\/04\/1514:00",
        "代辦業者": "慈航禮儀社",
        "公祭時間": ""
    },
    {
        "往生者姓名": "楊凱郎",
        "使用設備項目": "和平堂-48",
        "開始時間": "115\/04\/1514:10",
        "結束時間": "115\/04\/2013:50",
        "代辦業者": "慈航禮儀社",
        "公祭時間": "10:00"
    },
    {
        "往生者姓名": "楊凱郎",
        "使用設備項目": "遺體火化（第一火化場）",
        "開始時間": "115\/04\/20",
        "結束時間": "115\/04\/20",
        "代辦業者": "慈航禮儀社",
        "公祭時間": ""
    }
]