[
    {
        "往生者姓名": "蔡德容",
        "使用設備項目": "冷凍室-156",
        "開始時間": "115\/04\/2416:58",
        "結束時間": "115\/05\/0508:00",
        "代辦業者": "聖嵐人本生命事業有限公司",
        "公祭時間": ""
    },
    {
        "往生者姓名": "蔡德容",
        "使用設備項目": "豎靈區-017",
        "開始時間": "115\/04\/25",
        "結束時間": "115\/05\/0609:00",
        "代辦業者": "聖嵐人本生命事業有限公司",
        "公祭時間": ""
    },
    {
        "往生者姓名": "蔡德容",
        "使用設備項目": "和平堂-38",
        "開始時間": "115\/05\/0414:10",
        "結束時間": "115\/05\/0613:50",
        "代辦業者": "聖嵐人本生命事業有限公司",
        "公祭時間": "10:30"
    },
    {
        "往生者姓名": "蔡德容",
        "使用設備項目": "洗化室07",
        "開始時間": "115\/05\/0513:00",
        "結束時間": "115\/05\/0515:00",
        "代辦業者": "聖嵐人本生命事業有限公司",
        "公祭時間": ""
    },
    {
        "往生者姓名": "蔡德容",
        "使用設備項目": "停屍間",
        "開始時間": "115\/05\/06",
        "結束時間": "115\/05\/0608:00",
        "代辦業者": "聖嵐人本生命事業有限公司",
        "公祭時間": ""
    },
    {
        "往生者姓名": "蔡德容",
        "使用設備項目": "入殮室11",
        "開始時間": "115\/05\/0608:00",
        "結束時間": "115\/05\/0610:00",
        "代辦業者": "聖嵐人本生命事業有限公司",
        "公祭時間": ""
    },
    {
        "往生者姓名": "蔡德容",
        "使用設備項目": "遺體火化（第二火化場）",
        "開始時間": "115\/05\/06",
        "結束時間": "115\/05\/06",
        "代辦業者": "聖嵐人本生命事業有限公司",
        "公祭時間": ""
    }
]