[
    {
        "往生者姓名": "黃林菊枝",
        "使用設備項目": "冷凍室-163",
        "開始時間": "114\/10\/1211:22",
        "結束時間": "114\/10\/2109:00",
        "代辦業者": "永富禮儀社",
        "公祭時間": ""
    },
    {
        "往生者姓名": "黃林菊枝",
        "使用設備項目": "豎靈區-043",
        "開始時間": "114\/10\/13",
        "結束時間": "114\/10\/2211:00",
        "代辦業者": "永富禮儀社",
        "公祭時間": ""
    },
    {
        "往生者姓名": "黃林菊枝",
        "使用設備項目": "洗化室01",
        "開始時間": "114\/10\/21",
        "結束時間": "114\/10\/21",
        "代辦業者": "永富禮儀社",
        "公祭時間": ""
    },
    {
        "往生者姓名": "黃林菊枝",
        "使用設備項目": "和平堂-47",
        "開始時間": "114\/10\/2114:10",
        "結束時間": "114\/10\/2213:50",
        "代辦業者": "永富禮儀社",
        "公祭時間": "10:00"
    },
    {
        "往生者姓名": "黃林菊枝",
        "使用設備項目": "停屍間",
        "開始時間": "114\/10\/22",
        "結束時間": "114\/10\/2209:00",
        "代辦業者": "永富禮儀社",
        "公祭時間": ""
    },
    {
        "往生者姓名": "黃林菊枝",
        "使用設備項目": "入殮室10",
        "開始時間": "114\/10\/2209:00",
        "結束時間": "114\/10\/2211:00",
        "代辦業者": "永富禮儀社",
        "公祭時間": ""
    },
    {
        "往生者姓名": "黃林菊枝",
        "使用設備項目": "遺體火化",
        "開始時間": "114\/10\/22",
        "結束時間": "114\/10\/22",
        "代辦業者": "永富禮儀社",
        "公祭時間": ""
    }
]