[
    {
        "往生者姓名": "李廣勇",
        "使用設備項目": "冷凍室-035",
        "開始時間": "114\/10\/1619:16",
        "結束時間": "114\/10\/2407:00",
        "代辦業者": "豐聖禮儀社",
        "公祭時間": ""
    },
    {
        "往生者姓名": "李廣勇",
        "使用設備項目": "洗化室05",
        "開始時間": "114\/10\/24",
        "結束時間": "114\/10\/24",
        "代辦業者": "豐聖禮儀社",
        "公祭時間": ""
    },
    {
        "往生者姓名": "李廣勇",
        "使用設備項目": "停屍間",
        "開始時間": "114\/10\/25",
        "結束時間": "114\/10\/2507:00",
        "代辦業者": "豐聖禮儀社",
        "公祭時間": ""
    },
    {
        "往生者姓名": "李廣勇",
        "使用設備項目": "入殮(助念)室05",
        "開始時間": "114\/10\/2507:00",
        "結束時間": "114\/10\/2509:00",
        "代辦業者": "豐聖禮儀社",
        "公祭時間": ""
    },
    {
        "往生者姓名": "李廣勇",
        "使用設備項目": "至德廳",
        "開始時間": "114\/10\/2508:00",
        "結束時間": "114\/10\/2511:00",
        "代辦業者": "豐聖禮儀社",
        "公祭時間": "無公祭"
    },
    {
        "往生者姓名": "李廣勇",
        "使用設備項目": "遺體火化",
        "開始時間": "114\/10\/25",
        "結束時間": "114\/10\/25",
        "代辦業者": "豐聖禮儀社",
        "公祭時間": ""
    }
]