[
    {
        "往生者姓名": "楊秋龍",
        "使用設備項目": "冷凍室-204",
        "開始時間": "114\/06\/2510:02",
        "結束時間": "114\/06\/2612:00",
        "代辦業者": "統一禮儀社",
        "公祭時間": ""
    },
    {
        "往生者姓名": "楊秋龍",
        "使用設備項目": "洗化室06",
        "開始時間": "114\/06\/26",
        "結束時間": "114\/06\/26",
        "代辦業者": "統一禮儀社",
        "公祭時間": ""
    },
    {
        "往生者姓名": "楊秋龍",
        "使用設備項目": "入殮室08",
        "開始時間": "114\/06\/2612:00",
        "結束時間": "114\/06\/2614:00",
        "代辦業者": "統一禮儀社",
        "公祭時間": ""
    },
    {
        "往生者姓名": "楊秋龍",
        "使用設備項目": "永安堂-42",
        "開始時間": "114\/06\/2614:10",
        "結束時間": "114\/07\/0113:50",
        "代辦業者": "統一禮儀社",
        "公祭時間": "無公祭"
    },
    {
        "往生者姓名": "楊秋龍",
        "使用設備項目": "遺體火化",
        "開始時間": "114\/07\/01",
        "結束時間": "114\/07\/01",
        "代辦業者": "統一禮儀社",
        "公祭時間": ""
    }
]