[
    {
        "往生者姓名": "莊梅玲",
        "使用設備項目": "冷凍室-164",
        "開始時間": "115\/07\/0310:39",
        "結束時間": "115\/07\/0823:59",
        "代辦業者": "龍巖股份有限公司",
        "公祭時間": ""
    },
    {
        "往生者姓名": "莊梅玲",
        "使用設備項目": "洗化室08",
        "開始時間": "115\/07\/0900:00",
        "結束時間": "115\/07\/0906:00",
        "代辦業者": "龍巖股份有限公司",
        "公祭時間": ""
    },
    {
        "往生者姓名": "莊梅玲",
        "使用設備項目": "入殮室02",
        "開始時間": "115\/07\/0906:00",
        "結束時間": "115\/07\/0908:00",
        "代辦業者": "龍巖股份有限公司",
        "公祭時間": ""
    },
    {
        "往生者姓名": "莊梅玲",
        "使用設備項目": "懷悌廳",
        "開始時間": "115\/07\/0907:00",
        "結束時間": "115\/07\/0909:30",
        "代辦業者": "龍巖股份有限公司",
        "公祭時間": "無公祭"
    },
    {
        "往生者姓名": "莊梅玲",
        "使用設備項目": "遺體火化（第一火化場）",
        "開始時間": "115\/07\/09",
        "結束時間": "115\/07\/09",
        "代辦業者": "龍巖股份有限公司",
        "公祭時間": ""
    }
]