[
    {
        "往生者姓名": "吳敏正",
        "使用設備項目": "冷凍室-006",
        "開始時間": "114\/05\/3123:09",
        "結束時間": "114\/06\/1010:00",
        "代辦業者": "新界禮儀社",
        "公祭時間": ""
    },
    {
        "往生者姓名": "吳敏正",
        "使用設備項目": "豎靈區-027",
        "開始時間": "114\/06\/02",
        "結束時間": "114\/06\/1112:00",
        "代辦業者": "新界禮儀社",
        "公祭時間": ""
    },
    {
        "往生者姓名": "吳敏正",
        "使用設備項目": "洗化室04",
        "開始時間": "114\/06\/10",
        "結束時間": "114\/06\/10",
        "代辦業者": "新界禮儀社",
        "公祭時間": ""
    },
    {
        "往生者姓名": "吳敏正",
        "使用設備項目": "停屍間",
        "開始時間": "114\/06\/11",
        "結束時間": "114\/06\/1110:00",
        "代辦業者": "新界禮儀社",
        "公祭時間": ""
    },
    {
        "往生者姓名": "吳敏正",
        "使用設備項目": "遺體火化",
        "開始時間": "114\/06\/11",
        "結束時間": "114\/06\/11",
        "代辦業者": "新界禮儀社",
        "公祭時間": ""
    },
    {
        "往生者姓名": "吳敏正",
        "使用設備項目": "入殮室02",
        "開始時間": "114\/06\/1110:00",
        "結束時間": "114\/06\/1112:00",
        "代辦業者": "新界禮儀社",
        "公祭時間": "無公祭"
    }
]