[
    {
        "往生者姓名": "詹蕙茹",
        "使用設備項目": "景行無煙豎靈-006",
        "開始時間": "114\/05\/19",
        "結束時間": "114\/05\/2210:00",
        "代辦業者": "品閣禮儀社",
        "公祭時間": ""
    },
    {
        "往生者姓名": "詹蕙茹",
        "使用設備項目": "冷凍室-080",
        "開始時間": "114\/05\/1910:55",
        "結束時間": "114\/05\/2208:00",
        "代辦業者": "品閣禮儀社",
        "公祭時間": ""
    },
    {
        "往生者姓名": "詹蕙茹",
        "使用設備項目": "入殮(助念)室07",
        "開始時間": "114\/05\/2113:00",
        "結束時間": "114\/05\/2117:00",
        "代辦業者": "品閣禮儀社",
        "公祭時間": ""
    },
    {
        "往生者姓名": "詹蕙茹",
        "使用設備項目": "光德入殮02",
        "開始時間": "114\/05\/2208:00",
        "結束時間": "114\/05\/2210:00",
        "代辦業者": "品閣禮儀社",
        "公祭時間": "無公祭"
    }
]