[
    {
        "往生者姓名": "王凃桂妹",
        "使用設備項目": "冷凍室-201",
        "開始時間": "115\/05\/2313:32",
        "結束時間": "115\/05\/2908:00",
        "代辦業者": "龍巖股份有限公司",
        "公祭時間": ""
    },
    {
        "往生者姓名": "王凃桂妹",
        "使用設備項目": "洗化室08",
        "開始時間": "115\/05\/2909:00",
        "結束時間": "115\/05\/2911:00",
        "代辦業者": "龍巖股份有限公司",
        "公祭時間": ""
    },
    {
        "往生者姓名": "王凃桂妹",
        "使用設備項目": "停屍間",
        "開始時間": "115\/05\/30",
        "結束時間": "115\/05\/3008:00",
        "代辦業者": "龍巖股份有限公司",
        "公祭時間": ""
    },
    {
        "往生者姓名": "王凃桂妹",
        "使用設備項目": "懷悌廳",
        "開始時間": "115\/05\/3007:00",
        "結束時間": "115\/05\/3009:30",
        "代辦業者": "龍巖股份有限公司",
        "公祭時間": "無公祭"
    },
    {
        "往生者姓名": "王凃桂妹",
        "使用設備項目": "入殮室01",
        "開始時間": "115\/05\/3008:00",
        "結束時間": "115\/05\/3010:00",
        "代辦業者": "龍巖股份有限公司",
        "公祭時間": ""
    },
    {
        "往生者姓名": "王凃桂妹",
        "使用設備項目": "遺體火化（第一火化場）",
        "開始時間": "115\/05\/30",
        "結束時間": "115\/05\/30",
        "代辦業者": "龍巖股份有限公司",
        "公祭時間": ""
    },
    {
        "往生者姓名": "王凃桂妹",
        "使用設備項目": "懷悌廳",
        "開始時間": "115\/05\/3011:00",
        "結束時間": "115\/05\/3013:30",
        "代辦業者": "龍巖股份有限公司",
        "公祭時間": ""
    }
]