[
    {
        "往生者姓名": "林孝忠",
        "使用設備項目": "冷凍室-069",
        "開始時間": "114\/07\/0519:16",
        "結束時間": "114\/07\/0806:00",
        "代辦業者": "自成宇宙生命禮儀社",
        "公祭時間": ""
    },
    {
        "往生者姓名": "林孝忠",
        "使用設備項目": "洗化室05",
        "開始時間": "114\/07\/08",
        "結束時間": "114\/07\/08",
        "代辦業者": "自成宇宙生命禮儀社",
        "公祭時間": ""
    },
    {
        "往生者姓名": "林孝忠",
        "使用設備項目": "遺體火化",
        "開始時間": "114\/07\/09",
        "結束時間": "114\/07\/09",
        "代辦業者": "自成宇宙生命禮儀社",
        "公祭時間": ""
    },
    {
        "往生者姓名": "林孝忠",
        "使用設備項目": "停屍間",
        "開始時間": "114\/07\/09",
        "結束時間": "114\/07\/0906:00",
        "代辦業者": "自成宇宙生命禮儀社",
        "公祭時間": ""
    },
    {
        "往生者姓名": "林孝忠",
        "使用設備項目": "入殮室09",
        "開始時間": "114\/07\/0906:00",
        "結束時間": "114\/07\/0908:00",
        "代辦業者": "自成宇宙生命禮儀社",
        "公祭時間": "無公祭"
    }
]